{
  "name": "United States Of America",
  "slug": "united-states-of-america",
  "locale": "en-US",
  "invalidCount": 1194,
  "autoFixableCount": 12,
  "safeEditCount": 43,
  "totalNumbers": 728710,
  "groupedDivisionStats": {
    "United States Of America": [
      {
        "name": "Alabama",
        "divisionSlug": "united-states-of-america",
        "slug": "alabama",
        "invalidCount": 4,
        "autoFixableCount": 0,
        "safeEditCount": 0,
        "totalNumbers": 8136,
        "lastUpdated": "2025-12-15T03:21:44.470Z"
      },
      {
        "name": "Alaska",
        "divisionSlug": "united-states-of-america",
        "slug": "alaska",
        "invalidCount": 4,
        "autoFixableCount": 0,
        "safeEditCount": 1,
        "totalNumbers": 1895,
        "lastUpdated": "2025-12-15T03:22:09.189Z"
      },
      {
        "name": "American Samoa",
        "divisionSlug": "united-states-of-america",
        "slug": "american-samoa",
        "invalidCount": 0,
        "autoFixableCount": 0,
        "safeEditCount": 0,
        "totalNumbers": 7,
        "lastUpdated": "2025-12-15T03:22:10.193Z"
      },
      {
        "name": "Arizona",
        "divisionSlug": "united-states-of-america",
        "slug": "arizona",
        "invalidCount": 25,
        "autoFixableCount": 0,
        "safeEditCount": 0,
        "totalNumbers": 13769,
        "lastUpdated": "2025-12-15T03:22:54.376Z"
      },
      {
        "name": "Arkansas",
        "divisionSlug": "united-states-of-america",
        "slug": "arkansas",
        "invalidCount": 5,
        "autoFixableCount": 0,
        "safeEditCount": 0,
        "totalNumbers": 6198,
        "lastUpdated": "2025-12-15T03:23:06.848Z"
      },
      {
        "name": "California",
        "divisionSlug": "united-states-of-america",
        "slug": "california",
        "invalidCount": 245,
        "autoFixableCount": 2,
        "safeEditCount": 12,
        "totalNumbers": 68906,
        "lastUpdated": "2025-12-15T03:25:22.159Z"
      },
      {
        "name": "Colorado",
        "divisionSlug": "united-states-of-america",
        "slug": "colorado",
        "invalidCount": 27,
        "autoFixableCount": 0,
        "safeEditCount": 0,
        "totalNumbers": 21545,
        "lastUpdated": "2025-12-15T03:26:10.544Z"
      },
      {
        "name": "Connecticut",
        "divisionSlug": "united-states-of-america",
        "slug": "connecticut",
        "invalidCount": 16,
        "autoFixableCount": 0,
        "safeEditCount": 0,
        "totalNumbers": 9653,
        "lastUpdated": "2025-12-15T03:26:34.307Z"
      },
      {
        "name": "Delaware",
        "divisionSlug": "united-states-of-america",
        "slug": "delaware",
        "invalidCount": 0,
        "autoFixableCount": 0,
        "safeEditCount": 0,
        "totalNumbers": 2253,
        "lastUpdated": "2025-12-15T03:26:38.481Z"
      },
      {
        "name": "District of Columbia",
        "divisionSlug": "united-states-of-america",
        "slug": "district-of-columbia",
        "invalidCount": 0,
        "autoFixableCount": 0,
        "safeEditCount": 0,
        "totalNumbers": 3457,
        "lastUpdated": "2025-12-15T03:26:50.218Z"
      },
      {
        "name": "Florida",
        "divisionSlug": "united-states-of-america",
        "slug": "florida",
        "invalidCount": 33,
        "autoFixableCount": 0,
        "safeEditCount": 0,
        "totalNumbers": 31744,
        "lastUpdated": "2025-12-15T03:28:19.744Z"
      },
      {
        "name": "Georgia",
        "divisionSlug": "united-states-of-america",
        "slug": "georgia",
        "invalidCount": 33,
        "autoFixableCount": 1,
        "safeEditCount": 7,
        "totalNumbers": 20287,
        "lastUpdated": "2025-12-15T03:29:00.110Z"
      },
      {
        "name": "Guam",
        "divisionSlug": "united-states-of-america",
        "slug": "guam",
        "invalidCount": 0,
        "autoFixableCount": 0,
        "safeEditCount": 0,
        "totalNumbers": 125,
        "lastUpdated": "2025-12-15T03:29:01.812Z"
      },
      {
        "name": "Hawaii",
        "divisionSlug": "united-states-of-america",
        "slug": "hawaii",
        "invalidCount": 7,
        "autoFixableCount": 0,
        "safeEditCount": 0,
        "totalNumbers": 2210,
        "lastUpdated": "2025-12-15T03:29:07.143Z"
      },
      {
        "name": "Idaho",
        "divisionSlug": "united-states-of-america",
        "slug": "idaho",
        "invalidCount": 2,
        "autoFixableCount": 0,
        "safeEditCount": 0,
        "totalNumbers": 3586,
        "lastUpdated": "2025-12-15T03:29:27.612Z"
      },
      {
        "name": "Illinois",
        "divisionSlug": "united-states-of-america",
        "slug": "illinois",
        "invalidCount": 51,
        "autoFixableCount": 0,
        "safeEditCount": 3,
        "totalNumbers": 27848,
        "lastUpdated": "2025-12-15T03:30:17.127Z"
      },
      {
        "name": "Indiana",
        "divisionSlug": "united-states-of-america",
        "slug": "indiana",
        "invalidCount": 13,
        "autoFixableCount": 0,
        "safeEditCount": 0,
        "totalNumbers": 10348,
        "lastUpdated": "2025-12-15T03:30:42.968Z"
      },
      {
        "name": "Iowa",
        "divisionSlug": "united-states-of-america",
        "slug": "iowa",
        "invalidCount": 3,
        "autoFixableCount": 0,
        "safeEditCount": 0,
        "totalNumbers": 8619,
        "lastUpdated": "2025-12-15T03:31:03.851Z"
      },
      {
        "name": "Kansas",
        "divisionSlug": "united-states-of-america",
        "slug": "kansas",
        "invalidCount": 8,
        "autoFixableCount": 0,
        "safeEditCount": 2,
        "totalNumbers": 7576,
        "lastUpdated": "2025-12-15T03:31:19.337Z"
      },
      {
        "name": "Kentucky",
        "divisionSlug": "united-states-of-america",
        "slug": "kentucky",
        "invalidCount": 15,
        "autoFixableCount": 0,
        "safeEditCount": 0,
        "totalNumbers": 7089,
        "lastUpdated": "2025-12-15T03:31:40.609Z"
      },
      {
        "name": "Louisiana",
        "divisionSlug": "united-states-of-america",
        "slug": "louisiana",
        "invalidCount": 15,
        "autoFixableCount": 0,
        "safeEditCount": 0,
        "totalNumbers": 7686,
        "lastUpdated": "2025-12-15T03:31:58.334Z"
      },
      {
        "name": "Maine",
        "divisionSlug": "united-states-of-america",
        "slug": "maine",
        "invalidCount": 9,
        "autoFixableCount": 0,
        "safeEditCount": 9,
        "totalNumbers": 4140,
        "lastUpdated": "2025-12-15T03:32:16.190Z"
      },
      {
        "name": "Maryland",
        "divisionSlug": "united-states-of-america",
        "slug": "maryland",
        "invalidCount": 27,
        "autoFixableCount": 0,
        "safeEditCount": 0,
        "totalNumbers": 17759,
        "lastUpdated": "2025-12-15T03:32:50.220Z"
      },
      {
        "name": "Massachusetts",
        "divisionSlug": "united-states-of-america",
        "slug": "massachusetts",
        "invalidCount": 35,
        "autoFixableCount": 1,
        "safeEditCount": 0,
        "totalNumbers": 16063,
        "lastUpdated": "2025-12-15T03:33:27.303Z"
      },
      {
        "name": "Michigan",
        "divisionSlug": "united-states-of-america",
        "slug": "michigan",
        "invalidCount": 23,
        "autoFixableCount": 0,
        "safeEditCount": 0,
        "totalNumbers": 25735,
        "lastUpdated": "2025-12-15T03:34:08.566Z"
      },
      {
        "name": "Minnesota",
        "divisionSlug": "united-states-of-america",
        "slug": "minnesota",
        "invalidCount": 17,
        "autoFixableCount": 0,
        "safeEditCount": 0,
        "totalNumbers": 13332,
        "lastUpdated": "2025-12-15T03:34:43.649Z"
      },
      {
        "name": "Mississippi",
        "divisionSlug": "united-states-of-america",
        "slug": "mississippi",
        "invalidCount": 4,
        "autoFixableCount": 0,
        "safeEditCount": 0,
        "totalNumbers": 3912,
        "lastUpdated": "2025-12-15T03:34:55.571Z"
      },
      {
        "name": "Missouri",
        "divisionSlug": "united-states-of-america",
        "slug": "missouri",
        "invalidCount": 25,
        "autoFixableCount": 0,
        "safeEditCount": 0,
        "totalNumbers": 10614,
        "lastUpdated": "2025-12-15T03:35:25.461Z"
      },
      {
        "name": "Montana",
        "divisionSlug": "united-states-of-america",
        "slug": "montana",
        "invalidCount": 1,
        "autoFixableCount": 0,
        "safeEditCount": 0,
        "totalNumbers": 3032,
        "lastUpdated": "2025-12-15T03:35:39.498Z"
      },
      {
        "name": "Nebraska",
        "divisionSlug": "united-states-of-america",
        "slug": "nebraska",
        "invalidCount": 2,
        "autoFixableCount": 0,
        "safeEditCount": 0,
        "totalNumbers": 5532,
        "lastUpdated": "2025-12-15T03:35:54.641Z"
      },
      {
        "name": "Nevada",
        "divisionSlug": "united-states-of-america",
        "slug": "nevada",
        "invalidCount": 0,
        "autoFixableCount": 0,
        "safeEditCount": 0,
        "totalNumbers": 6121,
        "lastUpdated": "2025-12-15T03:36:16.475Z"
      },
      {
        "name": "New Hampshire",
        "divisionSlug": "united-states-of-america",
        "slug": "new-hampshire",
        "invalidCount": 3,
        "autoFixableCount": 3,
        "safeEditCount": 0,
        "totalNumbers": 5688,
        "lastUpdated": "2025-12-15T03:36:28.148Z"
      },
      {
        "name": "New Jersey",
        "divisionSlug": "united-states-of-america",
        "slug": "new-jersey",
        "invalidCount": 9,
        "autoFixableCount": 0,
        "safeEditCount": 1,
        "totalNumbers": 13033,
        "lastUpdated": "2025-12-15T03:36:59.848Z"
      },
      {
        "name": "New Mexico",
        "divisionSlug": "united-states-of-america",
        "slug": "new-mexico",
        "invalidCount": 11,
        "autoFixableCount": 0,
        "safeEditCount": 0,
        "totalNumbers": 6173,
        "lastUpdated": "2025-12-15T03:37:18.795Z"
      },
      {
        "name": "New York",
        "divisionSlug": "united-states-of-america",
        "slug": "new-york",
        "invalidCount": 151,
        "autoFixableCount": 1,
        "safeEditCount": 0,
        "totalNumbers": 54065,
        "lastUpdated": "2025-12-15T03:38:18.494Z"
      },
      {
        "name": "North Carolina",
        "divisionSlug": "united-states-of-america",
        "slug": "north-carolina",
        "invalidCount": 26,
        "autoFixableCount": 0,
        "safeEditCount": 2,
        "totalNumbers": 30375,
        "lastUpdated": "2025-12-15T03:39:04.449Z"
      },
      {
        "name": "North Dakota",
        "divisionSlug": "united-states-of-america",
        "slug": "north-dakota",
        "invalidCount": 0,
        "autoFixableCount": 0,
        "safeEditCount": 0,
        "totalNumbers": 1362,
        "lastUpdated": "2025-12-15T03:39:19.207Z"
      },
      {
        "name": "Northern Mariana Islands",
        "divisionSlug": "united-states-of-america",
        "slug": "northern-mariana-islands",
        "invalidCount": 0,
        "autoFixableCount": 0,
        "safeEditCount": 0,
        "totalNumbers": 52,
        "lastUpdated": "2025-12-15T03:39:20.367Z"
      },
      {
        "name": "Ohio",
        "divisionSlug": "united-states-of-america",
        "slug": "ohio",
        "invalidCount": 24,
        "autoFixableCount": 0,
        "safeEditCount": 0,
        "totalNumbers": 22863,
        "lastUpdated": "2025-12-15T03:39:55.999Z"
      },
      {
        "name": "Oklahoma",
        "divisionSlug": "united-states-of-america",
        "slug": "oklahoma",
        "invalidCount": 18,
        "autoFixableCount": 0,
        "safeEditCount": 0,
        "totalNumbers": 6838,
        "lastUpdated": "2025-12-15T03:40:14.533Z"
      },
      {
        "name": "Oregon",
        "divisionSlug": "united-states-of-america",
        "slug": "oregon",
        "invalidCount": 25,
        "autoFixableCount": 1,
        "safeEditCount": 0,
        "totalNumbers": 21412,
        "lastUpdated": "2025-12-15T03:40:46.428Z"
      },
      {
        "name": "Pennsylvania",
        "divisionSlug": "united-states-of-america",
        "slug": "pennsylvania",
        "invalidCount": 40,
        "autoFixableCount": 1,
        "safeEditCount": 0,
        "totalNumbers": 35165,
        "lastUpdated": "2025-12-15T03:41:31.219Z"
      },
      {
        "name": "Puerto Rico",
        "divisionSlug": "united-states-of-america",
        "slug": "puerto-rico",
        "invalidCount": 24,
        "autoFixableCount": 0,
        "safeEditCount": 0,
        "totalNumbers": 5202,
        "lastUpdated": "2025-12-15T03:41:40.340Z"
      },
      {
        "name": "Rhode Island",
        "divisionSlug": "united-states-of-america",
        "slug": "rhode-island",
        "invalidCount": 31,
        "autoFixableCount": 0,
        "safeEditCount": 1,
        "totalNumbers": 2026,
        "lastUpdated": "2025-12-15T03:41:46.286Z"
      },
      {
        "name": "South Carolina",
        "divisionSlug": "united-states-of-america",
        "slug": "south-carolina",
        "invalidCount": 19,
        "autoFixableCount": 0,
        "safeEditCount": 0,
        "totalNumbers": 10469,
        "lastUpdated": "2025-12-15T03:42:10.626Z"
      },
      {
        "name": "South Dakota",
        "divisionSlug": "united-states-of-america",
        "slug": "south-dakota",
        "invalidCount": 2,
        "autoFixableCount": 0,
        "safeEditCount": 0,
        "totalNumbers": 1955,
        "lastUpdated": "2025-12-15T03:42:18.597Z"
      },
      {
        "name": "Tennessee",
        "divisionSlug": "united-states-of-america",
        "slug": "tennessee",
        "invalidCount": 17,
        "autoFixableCount": 1,
        "safeEditCount": 1,
        "totalNumbers": 10979,
        "lastUpdated": "2025-12-15T03:42:42.650Z"
      },
      {
        "name": "Texas",
        "divisionSlug": "united-states-of-america",
        "slug": "texas",
        "invalidCount": 78,
        "autoFixableCount": 1,
        "safeEditCount": 3,
        "totalNumbers": 52866,
        "lastUpdated": "2025-12-15T03:43:59.391Z"
      },
      {
        "name": "United States Virgin Islands",
        "divisionSlug": "united-states-of-america",
        "slug": "united-states-virgin-islands",
        "invalidCount": 0,
        "autoFixableCount": 0,
        "safeEditCount": 0,
        "totalNumbers": 87,
        "lastUpdated": "2025-12-15T03:44:01.816Z"
      },
      {
        "name": "Utah",
        "divisionSlug": "united-states-of-america",
        "slug": "utah",
        "invalidCount": 22,
        "autoFixableCount": 0,
        "safeEditCount": 0,
        "totalNumbers": 9457,
        "lastUpdated": "2025-12-15T03:44:23.813Z"
      },
      {
        "name": "Vermont",
        "divisionSlug": "united-states-of-america",
        "slug": "vermont",
        "invalidCount": 0,
        "autoFixableCount": 0,
        "safeEditCount": 0,
        "totalNumbers": 2620,
        "lastUpdated": "2025-12-15T03:44:30.511Z"
      },
      {
        "name": "Virginia",
        "divisionSlug": "united-states-of-america",
        "slug": "virginia",
        "invalidCount": 30,
        "autoFixableCount": 0,
        "safeEditCount": 0,
        "totalNumbers": 26023,
        "lastUpdated": "2025-12-15T03:45:18.178Z"
      },
      {
        "name": "Washington",
        "divisionSlug": "united-states-of-america",
        "slug": "washington",
        "invalidCount": 0,
        "autoFixableCount": 0,
        "safeEditCount": 1,
        "totalNumbers": 19962,
        "lastUpdated": "2025-12-15T03:45:59.792Z"
      },
      {
        "name": "West Virginia",
        "divisionSlug": "united-states-of-america",
        "slug": "west-virginia",
        "invalidCount": 0,
        "autoFixableCount": 0,
        "safeEditCount": 0,
        "totalNumbers": 2891,
        "lastUpdated": "2025-12-15T03:46:15.533Z"
      },
      {
        "name": "Wisconsin",
        "divisionSlug": "united-states-of-america",
        "slug": "wisconsin",
        "invalidCount": 15,
        "autoFixableCount": 0,
        "safeEditCount": 0,
        "totalNumbers": 15589,
        "lastUpdated": "2025-12-15T03:46:50.489Z"
      },
      {
        "name": "Wyoming",
        "divisionSlug": "united-states-of-america",
        "slug": "wyoming",
        "invalidCount": 0,
        "autoFixableCount": 0,
        "safeEditCount": 0,
        "totalNumbers": 2381,
        "lastUpdated": "2025-12-15T03:47:01.863Z"
      }
    ]
  },
  "botEnabled": true
}