{
  "name": "United States Of America",
  "slug": "united-states-of-america",
  "locale": "en-US",
  "invalidCount": 1051,
  "autoFixableCount": 7,
  "safeEditCount": 48,
  "totalNumbers": 740110,
  "groupedDivisionStats": {
    "United States Of America": [
      {
        "name": "Alabama",
        "divisionSlug": "united-states-of-america",
        "slug": "alabama",
        "invalidCount": 3,
        "autoFixableCount": 0,
        "safeEditCount": 0,
        "totalNumbers": 8226,
        "lastUpdated": "2026-01-16T04:43:47.955Z"
      },
      {
        "name": "Alaska",
        "divisionSlug": "united-states-of-america",
        "slug": "alaska",
        "invalidCount": 4,
        "autoFixableCount": 0,
        "safeEditCount": 0,
        "totalNumbers": 1929,
        "lastUpdated": "2026-01-16T04:44:27.379Z"
      },
      {
        "name": "American Samoa",
        "divisionSlug": "united-states-of-america",
        "slug": "american-samoa",
        "invalidCount": 0,
        "autoFixableCount": 0,
        "safeEditCount": 0,
        "totalNumbers": 7,
        "lastUpdated": "2026-01-16T04:44:28.874Z"
      },
      {
        "name": "Arizona",
        "divisionSlug": "united-states-of-america",
        "slug": "arizona",
        "invalidCount": 23,
        "autoFixableCount": 0,
        "safeEditCount": 0,
        "totalNumbers": 13883,
        "lastUpdated": "2026-01-16T04:46:23.432Z"
      },
      {
        "name": "Arkansas",
        "divisionSlug": "united-states-of-america",
        "slug": "arkansas",
        "invalidCount": 5,
        "autoFixableCount": 0,
        "safeEditCount": 0,
        "totalNumbers": 6230,
        "lastUpdated": "2026-01-16T04:47:44.737Z"
      },
      {
        "name": "California",
        "divisionSlug": "united-states-of-america",
        "slug": "california",
        "invalidCount": 229,
        "autoFixableCount": 0,
        "safeEditCount": 3,
        "totalNumbers": 70155,
        "lastUpdated": "2026-01-16T04:50:04.116Z"
      },
      {
        "name": "Colorado",
        "divisionSlug": "united-states-of-america",
        "slug": "colorado",
        "invalidCount": 8,
        "autoFixableCount": 0,
        "safeEditCount": 1,
        "totalNumbers": 21901,
        "lastUpdated": "2026-01-16T04:51:01.336Z"
      },
      {
        "name": "Connecticut",
        "divisionSlug": "united-states-of-america",
        "slug": "connecticut",
        "invalidCount": 16,
        "autoFixableCount": 0,
        "safeEditCount": 0,
        "totalNumbers": 9694,
        "lastUpdated": "2026-01-16T04:51:31.234Z"
      },
      {
        "name": "Delaware",
        "divisionSlug": "united-states-of-america",
        "slug": "delaware",
        "invalidCount": 0,
        "autoFixableCount": 0,
        "safeEditCount": 0,
        "totalNumbers": 2312,
        "lastUpdated": "2026-01-16T04:51:36.922Z"
      },
      {
        "name": "District of Columbia",
        "divisionSlug": "united-states-of-america",
        "slug": "district-of-columbia",
        "invalidCount": 0,
        "autoFixableCount": 0,
        "safeEditCount": 0,
        "totalNumbers": 3629,
        "lastUpdated": "2026-01-16T04:51:55.192Z"
      },
      {
        "name": "Florida",
        "divisionSlug": "united-states-of-america",
        "slug": "florida",
        "invalidCount": 36,
        "autoFixableCount": 0,
        "safeEditCount": 5,
        "totalNumbers": 32212,
        "lastUpdated": "2026-01-16T04:54:20.009Z"
      },
      {
        "name": "Georgia",
        "divisionSlug": "united-states-of-america",
        "slug": "georgia",
        "invalidCount": 31,
        "autoFixableCount": 1,
        "safeEditCount": 2,
        "totalNumbers": 20668,
        "lastUpdated": "2026-01-16T04:55:00.069Z"
      },
      {
        "name": "Guam",
        "divisionSlug": "united-states-of-america",
        "slug": "guam",
        "invalidCount": 0,
        "autoFixableCount": 0,
        "safeEditCount": 0,
        "totalNumbers": 125,
        "lastUpdated": "2026-01-16T04:55:01.628Z"
      },
      {
        "name": "Hawaii",
        "divisionSlug": "united-states-of-america",
        "slug": "hawaii",
        "invalidCount": 7,
        "autoFixableCount": 0,
        "safeEditCount": 0,
        "totalNumbers": 2273,
        "lastUpdated": "2026-01-16T04:56:14.751Z"
      },
      {
        "name": "Idaho",
        "divisionSlug": "united-states-of-america",
        "slug": "idaho",
        "invalidCount": 3,
        "autoFixableCount": 0,
        "safeEditCount": 0,
        "totalNumbers": 3633,
        "lastUpdated": "2026-01-16T04:56:37.702Z"
      },
      {
        "name": "Illinois",
        "divisionSlug": "united-states-of-america",
        "slug": "illinois",
        "invalidCount": 37,
        "autoFixableCount": 0,
        "safeEditCount": 0,
        "totalNumbers": 28930,
        "lastUpdated": "2026-01-16T04:57:41.903Z"
      },
      {
        "name": "Indiana",
        "divisionSlug": "united-states-of-america",
        "slug": "indiana",
        "invalidCount": 13,
        "autoFixableCount": 0,
        "safeEditCount": 1,
        "totalNumbers": 10446,
        "lastUpdated": "2026-01-16T04:59:19.114Z"
      },
      {
        "name": "Iowa",
        "divisionSlug": "united-states-of-america",
        "slug": "iowa",
        "invalidCount": 1,
        "autoFixableCount": 0,
        "safeEditCount": 1,
        "totalNumbers": 8704,
        "lastUpdated": "2026-01-16T04:59:36.333Z"
      },
      {
        "name": "Kansas",
        "divisionSlug": "united-states-of-america",
        "slug": "kansas",
        "invalidCount": 7,
        "autoFixableCount": 0,
        "safeEditCount": 3,
        "totalNumbers": 7659,
        "lastUpdated": "2026-01-16T04:59:53.492Z"
      },
      {
        "name": "Kentucky",
        "divisionSlug": "united-states-of-america",
        "slug": "kentucky",
        "invalidCount": 13,
        "autoFixableCount": 0,
        "safeEditCount": 3,
        "totalNumbers": 7148,
        "lastUpdated": "2026-01-16T05:00:16.134Z"
      },
      {
        "name": "Louisiana",
        "divisionSlug": "united-states-of-america",
        "slug": "louisiana",
        "invalidCount": 14,
        "autoFixableCount": 0,
        "safeEditCount": 0,
        "totalNumbers": 7929,
        "lastUpdated": "2026-01-16T05:01:39.808Z"
      },
      {
        "name": "Maine",
        "divisionSlug": "united-states-of-america",
        "slug": "maine",
        "invalidCount": 9,
        "autoFixableCount": 0,
        "safeEditCount": 0,
        "totalNumbers": 4221,
        "lastUpdated": "2026-01-16T05:01:56.251Z"
      },
      {
        "name": "Maryland",
        "divisionSlug": "united-states-of-america",
        "slug": "maryland",
        "invalidCount": 24,
        "autoFixableCount": 0,
        "safeEditCount": 0,
        "totalNumbers": 18127,
        "lastUpdated": "2026-01-16T05:02:30.880Z"
      },
      {
        "name": "Massachusetts",
        "divisionSlug": "united-states-of-america",
        "slug": "massachusetts",
        "invalidCount": 36,
        "autoFixableCount": 2,
        "safeEditCount": 1,
        "totalNumbers": 16241,
        "lastUpdated": "2026-01-16T05:03:07.550Z"
      },
      {
        "name": "Michigan",
        "divisionSlug": "united-states-of-america",
        "slug": "michigan",
        "invalidCount": 23,
        "autoFixableCount": 0,
        "safeEditCount": 0,
        "totalNumbers": 25917,
        "lastUpdated": "2026-01-16T05:03:51.674Z"
      },
      {
        "name": "Minnesota",
        "divisionSlug": "united-states-of-america",
        "slug": "minnesota",
        "invalidCount": 18,
        "autoFixableCount": 0,
        "safeEditCount": 0,
        "totalNumbers": 13409,
        "lastUpdated": "2026-01-16T05:04:28.177Z"
      },
      {
        "name": "Mississippi",
        "divisionSlug": "united-states-of-america",
        "slug": "mississippi",
        "invalidCount": 4,
        "autoFixableCount": 0,
        "safeEditCount": 0,
        "totalNumbers": 3958,
        "lastUpdated": "2026-01-16T05:04:39.768Z"
      },
      {
        "name": "Missouri",
        "divisionSlug": "united-states-of-america",
        "slug": "missouri",
        "invalidCount": 25,
        "autoFixableCount": 0,
        "safeEditCount": 3,
        "totalNumbers": 10731,
        "lastUpdated": "2026-01-16T05:05:06.290Z"
      },
      {
        "name": "Montana",
        "divisionSlug": "united-states-of-america",
        "slug": "montana",
        "invalidCount": 1,
        "autoFixableCount": 0,
        "safeEditCount": 0,
        "totalNumbers": 3055,
        "lastUpdated": "2026-01-16T05:05:22.151Z"
      },
      {
        "name": "Nebraska",
        "divisionSlug": "united-states-of-america",
        "slug": "nebraska",
        "invalidCount": 2,
        "autoFixableCount": 0,
        "safeEditCount": 0,
        "totalNumbers": 5543,
        "lastUpdated": "2026-01-16T05:06:42.923Z"
      },
      {
        "name": "Nevada",
        "divisionSlug": "united-states-of-america",
        "slug": "nevada",
        "invalidCount": 0,
        "autoFixableCount": 0,
        "safeEditCount": 0,
        "totalNumbers": 6179,
        "lastUpdated": "2026-01-16T05:07:02.691Z"
      },
      {
        "name": "New Hampshire",
        "divisionSlug": "united-states-of-america",
        "slug": "new-hampshire",
        "invalidCount": 0,
        "autoFixableCount": 0,
        "safeEditCount": 0,
        "totalNumbers": 5750,
        "lastUpdated": "2026-01-16T05:07:13.982Z"
      },
      {
        "name": "New Jersey",
        "divisionSlug": "united-states-of-america",
        "slug": "new-jersey",
        "invalidCount": 10,
        "autoFixableCount": 0,
        "safeEditCount": 1,
        "totalNumbers": 13206,
        "lastUpdated": "2026-01-16T05:07:44.377Z"
      },
      {
        "name": "New Mexico",
        "divisionSlug": "united-states-of-america",
        "slug": "new-mexico",
        "invalidCount": 11,
        "autoFixableCount": 0,
        "safeEditCount": 0,
        "totalNumbers": 6229,
        "lastUpdated": "2026-01-16T05:08:05.084Z"
      },
      {
        "name": "New York",
        "divisionSlug": "united-states-of-america",
        "slug": "new-york",
        "invalidCount": 132,
        "autoFixableCount": 0,
        "safeEditCount": 1,
        "totalNumbers": 54585,
        "lastUpdated": "2026-01-16T05:09:08.561Z"
      },
      {
        "name": "North Carolina",
        "divisionSlug": "united-states-of-america",
        "slug": "north-carolina",
        "invalidCount": 23,
        "autoFixableCount": 0,
        "safeEditCount": 5,
        "totalNumbers": 30753,
        "lastUpdated": "2026-01-16T05:09:59.375Z"
      },
      {
        "name": "North Dakota",
        "divisionSlug": "united-states-of-america",
        "slug": "north-dakota",
        "invalidCount": 0,
        "autoFixableCount": 0,
        "safeEditCount": 0,
        "totalNumbers": 1366,
        "lastUpdated": "2026-01-16T05:10:13.903Z"
      },
      {
        "name": "Northern Mariana Islands",
        "divisionSlug": "united-states-of-america",
        "slug": "northern-mariana-islands",
        "invalidCount": 0,
        "autoFixableCount": 0,
        "safeEditCount": 0,
        "totalNumbers": 52,
        "lastUpdated": "2026-01-16T05:10:15.136Z"
      },
      {
        "name": "Ohio",
        "divisionSlug": "united-states-of-america",
        "slug": "ohio",
        "invalidCount": 26,
        "autoFixableCount": 0,
        "safeEditCount": 3,
        "totalNumbers": 22980,
        "lastUpdated": "2026-01-16T05:10:54.982Z"
      },
      {
        "name": "Oklahoma",
        "divisionSlug": "united-states-of-america",
        "slug": "oklahoma",
        "invalidCount": 16,
        "autoFixableCount": 0,
        "safeEditCount": 1,
        "totalNumbers": 6910,
        "lastUpdated": "2026-01-16T05:11:16.961Z"
      },
      {
        "name": "Oregon",
        "divisionSlug": "united-states-of-america",
        "slug": "oregon",
        "invalidCount": 28,
        "autoFixableCount": 0,
        "safeEditCount": 0,
        "totalNumbers": 21675,
        "lastUpdated": "2026-01-16T05:11:50.684Z"
      },
      {
        "name": "Pennsylvania",
        "divisionSlug": "united-states-of-america",
        "slug": "pennsylvania",
        "invalidCount": 41,
        "autoFixableCount": 0,
        "safeEditCount": 2,
        "totalNumbers": 36003,
        "lastUpdated": "2026-01-16T05:12:36.886Z"
      },
      {
        "name": "Puerto Rico",
        "divisionSlug": "united-states-of-america",
        "slug": "puerto-rico",
        "invalidCount": 24,
        "autoFixableCount": 0,
        "safeEditCount": 0,
        "totalNumbers": 5206,
        "lastUpdated": "2026-01-16T05:12:51.424Z"
      },
      {
        "name": "Rhode Island",
        "divisionSlug": "united-states-of-america",
        "slug": "rhode-island",
        "invalidCount": 22,
        "autoFixableCount": 0,
        "safeEditCount": 0,
        "totalNumbers": 2034,
        "lastUpdated": "2026-01-16T05:12:57.792Z"
      },
      {
        "name": "South Carolina",
        "divisionSlug": "united-states-of-america",
        "slug": "south-carolina",
        "invalidCount": 19,
        "autoFixableCount": 0,
        "safeEditCount": 0,
        "totalNumbers": 10649,
        "lastUpdated": "2026-01-16T05:13:21.128Z"
      },
      {
        "name": "South Dakota",
        "divisionSlug": "united-states-of-america",
        "slug": "south-dakota",
        "invalidCount": 2,
        "autoFixableCount": 0,
        "safeEditCount": 0,
        "totalNumbers": 2004,
        "lastUpdated": "2026-01-16T05:14:38.994Z"
      },
      {
        "name": "Tennessee",
        "divisionSlug": "united-states-of-america",
        "slug": "tennessee",
        "invalidCount": 15,
        "autoFixableCount": 0,
        "safeEditCount": 0,
        "totalNumbers": 11034,
        "lastUpdated": "2026-01-16T05:15:02.643Z"
      },
      {
        "name": "Texas",
        "divisionSlug": "united-states-of-america",
        "slug": "texas",
        "invalidCount": 29,
        "autoFixableCount": 2,
        "safeEditCount": 6,
        "totalNumbers": 53584,
        "lastUpdated": "2026-01-16T05:16:27.578Z"
      },
      {
        "name": "United States Virgin Islands",
        "divisionSlug": "united-states-of-america",
        "slug": "united-states-virgin-islands",
        "invalidCount": 0,
        "autoFixableCount": 0,
        "safeEditCount": 0,
        "totalNumbers": 88,
        "lastUpdated": "2026-01-16T05:16:29.390Z"
      },
      {
        "name": "Utah",
        "divisionSlug": "united-states-of-america",
        "slug": "utah",
        "invalidCount": 21,
        "autoFixableCount": 0,
        "safeEditCount": 0,
        "totalNumbers": 9582,
        "lastUpdated": "2026-01-16T05:16:49.859Z"
      },
      {
        "name": "Vermont",
        "divisionSlug": "united-states-of-america",
        "slug": "vermont",
        "invalidCount": 0,
        "autoFixableCount": 0,
        "safeEditCount": 1,
        "totalNumbers": 2647,
        "lastUpdated": "2026-01-16T05:16:57.018Z"
      },
      {
        "name": "Virginia",
        "divisionSlug": "united-states-of-america",
        "slug": "virginia",
        "invalidCount": 21,
        "autoFixableCount": 0,
        "safeEditCount": 0,
        "totalNumbers": 26761,
        "lastUpdated": "2026-01-16T05:18:56.064Z"
      },
      {
        "name": "Washington",
        "divisionSlug": "united-states-of-america",
        "slug": "washington",
        "invalidCount": 2,
        "autoFixableCount": 1,
        "safeEditCount": 3,
        "totalNumbers": 20920,
        "lastUpdated": "2026-01-16T05:19:44.961Z"
      },
      {
        "name": "West Virginia",
        "divisionSlug": "united-states-of-america",
        "slug": "west-virginia",
        "invalidCount": 0,
        "autoFixableCount": 0,
        "safeEditCount": 0,
        "totalNumbers": 2904,
        "lastUpdated": "2026-01-16T05:20:01.409Z"
      },
      {
        "name": "Wisconsin",
        "divisionSlug": "united-states-of-america",
        "slug": "wisconsin",
        "invalidCount": 17,
        "autoFixableCount": 1,
        "safeEditCount": 2,
        "totalNumbers": 15714,
        "lastUpdated": "2026-01-16T05:20:41.120Z"
      },
      {
        "name": "Wyoming",
        "divisionSlug": "united-states-of-america",
        "slug": "wyoming",
        "invalidCount": 0,
        "autoFixableCount": 0,
        "safeEditCount": 0,
        "totalNumbers": 2400,
        "lastUpdated": "2026-01-16T05:22:02.125Z"
      }
    ]
  },
  "botEnabled": true
}