{
  "name": "España",
  "slug": "españa",
  "locale": "es-ES",
  "timestamp": "2026-05-23T00:00:00.000Z",
  "groupedDivisionStats": {
    "España": [
      {
        "name": "Andalucía",
        "divisionSlug": "españa",
        "slug": "andalucía",
        "lastUpdated": "2026-05-23T00:00:00.000Z",
        "invalidCount": 258,
        "autoFixableCount": 212,
        "totalCount": 14918
      },
      {
        "name": "Aragón",
        "divisionSlug": "españa",
        "slug": "aragón",
        "lastUpdated": "2026-05-23T00:00:00.000Z",
        "invalidCount": 27,
        "autoFixableCount": 11,
        "totalCount": 2972
      },
      {
        "name": "Asturias",
        "divisionSlug": "españa",
        "slug": "asturias",
        "lastUpdated": "2026-05-23T00:00:00.000Z",
        "invalidCount": 35,
        "autoFixableCount": 27,
        "totalCount": 1711
      },
      {
        "name": "Islas Baleares",
        "divisionSlug": "españa",
        "slug": "islas-baleares",
        "lastUpdated": "2026-05-23T00:00:00.000Z",
        "invalidCount": 36,
        "autoFixableCount": 27,
        "totalCount": 2807
      },
      {
        "name": "Islas Canarias",
        "divisionSlug": "españa",
        "slug": "islas-canarias",
        "lastUpdated": "2026-05-23T00:00:00.000Z",
        "invalidCount": 115,
        "autoFixableCount": 83,
        "totalCount": 5889
      },
      {
        "name": "Cantabria",
        "divisionSlug": "españa",
        "slug": "cantabria",
        "lastUpdated": "2026-05-23T00:00:00.000Z",
        "invalidCount": 39,
        "autoFixableCount": 34,
        "totalCount": 2769
      },
      {
        "name": "Castilla-La Mancha",
        "divisionSlug": "españa",
        "slug": "castilla-la-mancha",
        "lastUpdated": "2026-05-23T00:00:00.000Z",
        "invalidCount": 53,
        "autoFixableCount": 29,
        "totalCount": 3851
      },
      {
        "name": "Castilla y León",
        "divisionSlug": "españa",
        "slug": "castilla-y-león",
        "lastUpdated": "2026-05-23T00:00:00.000Z",
        "invalidCount": 105,
        "autoFixableCount": 85,
        "totalCount": 7882
      },
      {
        "name": "Cataluña",
        "divisionSlug": "españa",
        "slug": "cataluña",
        "lastUpdated": "2026-05-23T00:00:00.000Z",
        "invalidCount": 379,
        "autoFixableCount": 277,
        "totalCount": 20226
      },
      {
        "name": "Comunidad Valenciana",
        "divisionSlug": "españa",
        "slug": "comunidad-valenciana",
        "lastUpdated": "2026-05-23T00:00:00.000Z",
        "invalidCount": 209,
        "autoFixableCount": 148,
        "totalCount": 7650
      },
      {
        "name": "Extremadura",
        "divisionSlug": "españa",
        "slug": "extremadura",
        "lastUpdated": "2026-05-23T00:00:00.000Z",
        "invalidCount": 20,
        "autoFixableCount": 14,
        "totalCount": 1058
      },
      {
        "name": "Galicia",
        "divisionSlug": "españa",
        "slug": "galicia",
        "lastUpdated": "2026-05-23T00:00:00.000Z",
        "invalidCount": 207,
        "autoFixableCount": 168,
        "totalCount": 6565
      },
      {
        "name": "La Rioja",
        "divisionSlug": "españa",
        "slug": "la-rioja",
        "lastUpdated": "2026-05-23T00:00:00.000Z",
        "invalidCount": 6,
        "autoFixableCount": 3,
        "totalCount": 353
      },
      {
        "name": "Comunidad de Madrid",
        "divisionSlug": "españa",
        "slug": "comunidad-de-madrid",
        "lastUpdated": "2026-05-23T00:00:00.000Z",
        "invalidCount": 162,
        "autoFixableCount": 111,
        "totalCount": 9250
      },
      {
        "name": "Región de Murcia",
        "divisionSlug": "españa",
        "slug": "región-de-murcia",
        "lastUpdated": "2026-05-23T00:00:00.000Z",
        "invalidCount": 77,
        "autoFixableCount": 12,
        "totalCount": 1525
      },
      {
        "name": "Comunidad Foral de Navarra",
        "divisionSlug": "españa",
        "slug": "comunidad-foral-de-navarra",
        "lastUpdated": "2026-05-23T00:00:00.000Z",
        "invalidCount": 30,
        "autoFixableCount": 18,
        "totalCount": 1214
      },
      {
        "name": "País Vasco",
        "divisionSlug": "españa",
        "slug": "país-vasco",
        "lastUpdated": "2026-05-23T00:00:00.000Z",
        "invalidCount": 86,
        "autoFixableCount": 55,
        "totalCount": 3810
      },
      {
        "name": "Ceuta",
        "divisionSlug": "españa",
        "slug": "ceuta",
        "lastUpdated": "2026-05-23T00:00:00.000Z",
        "invalidCount": 0,
        "autoFixableCount": 0,
        "totalCount": 19
      },
      {
        "name": "Melilla",
        "divisionSlug": "españa",
        "slug": "melilla",
        "lastUpdated": "2026-05-23T00:00:00.000Z",
        "invalidCount": 0,
        "autoFixableCount": 0,
        "totalCount": 26
      }
    ]
  },
  "invalidCount": 1844,
  "autoFixableCount": 1314,
  "totalCount": 94495,
  "safeEditCount": 0
}