{
  "name": "United States Of America",
  "slug": "united-states-of-america",
  "locale": "en-US",
  "invalidCount": 1043,
  "autoFixableCount": 3,
  "safeEditCount": 45,
  "totalNumbers": 748876,
  "groupedDivisionStats": {
    "United States Of America": [
      {
        "name": "Alabama",
        "divisionSlug": "united-states-of-america",
        "slug": "alabama",
        "invalidCount": 5,
        "autoFixableCount": 0,
        "safeEditCount": 0,
        "totalNumbers": 8407,
        "lastUpdated": "2026-02-12T05:10:32.748Z"
      },
      {
        "name": "Alaska",
        "divisionSlug": "united-states-of-america",
        "slug": "alaska",
        "invalidCount": 4,
        "autoFixableCount": 0,
        "safeEditCount": 0,
        "totalNumbers": 1944,
        "lastUpdated": "2026-02-12T05:11:02.671Z"
      },
      {
        "name": "American Samoa",
        "divisionSlug": "united-states-of-america",
        "slug": "american-samoa",
        "invalidCount": 0,
        "autoFixableCount": 0,
        "safeEditCount": 0,
        "totalNumbers": 7,
        "lastUpdated": "2026-02-12T05:11:05.857Z"
      },
      {
        "name": "Arizona",
        "divisionSlug": "united-states-of-america",
        "slug": "arizona",
        "invalidCount": 24,
        "autoFixableCount": 1,
        "safeEditCount": 1,
        "totalNumbers": 14010,
        "lastUpdated": "2026-02-12T05:11:57.051Z"
      },
      {
        "name": "Arkansas",
        "divisionSlug": "united-states-of-america",
        "slug": "arkansas",
        "invalidCount": 5,
        "autoFixableCount": 0,
        "safeEditCount": 0,
        "totalNumbers": 6264,
        "lastUpdated": "2026-02-12T05:12:13.183Z"
      },
      {
        "name": "California",
        "divisionSlug": "united-states-of-america",
        "slug": "california",
        "invalidCount": 227,
        "autoFixableCount": 0,
        "safeEditCount": 6,
        "totalNumbers": 71270,
        "lastUpdated": "2026-02-12T05:14:48.427Z"
      },
      {
        "name": "Colorado",
        "divisionSlug": "united-states-of-america",
        "slug": "colorado",
        "invalidCount": 9,
        "autoFixableCount": 0,
        "safeEditCount": 2,
        "totalNumbers": 22032,
        "lastUpdated": "2026-02-12T05:15:37.482Z"
      },
      {
        "name": "Connecticut",
        "divisionSlug": "united-states-of-america",
        "slug": "connecticut",
        "invalidCount": 17,
        "autoFixableCount": 0,
        "safeEditCount": 0,
        "totalNumbers": 9753,
        "lastUpdated": "2026-02-12T05:16:06.622Z"
      },
      {
        "name": "Delaware",
        "divisionSlug": "united-states-of-america",
        "slug": "delaware",
        "invalidCount": 0,
        "autoFixableCount": 0,
        "safeEditCount": 0,
        "totalNumbers": 2379,
        "lastUpdated": "2026-02-12T05:16:15.379Z"
      },
      {
        "name": "District of Columbia",
        "divisionSlug": "united-states-of-america",
        "slug": "district-of-columbia",
        "invalidCount": 0,
        "autoFixableCount": 0,
        "safeEditCount": 0,
        "totalNumbers": 3688,
        "lastUpdated": "2026-02-12T05:16:32.176Z"
      },
      {
        "name": "Florida",
        "divisionSlug": "united-states-of-america",
        "slug": "florida",
        "invalidCount": 37,
        "autoFixableCount": 0,
        "safeEditCount": 2,
        "totalNumbers": 32612,
        "lastUpdated": "2026-02-12T05:18:10.479Z"
      },
      {
        "name": "Georgia",
        "divisionSlug": "united-states-of-america",
        "slug": "georgia",
        "invalidCount": 29,
        "autoFixableCount": 0,
        "safeEditCount": 0,
        "totalNumbers": 21066,
        "lastUpdated": "2026-02-12T05:18:58.496Z"
      },
      {
        "name": "Guam",
        "divisionSlug": "united-states-of-america",
        "slug": "guam",
        "invalidCount": 0,
        "autoFixableCount": 0,
        "safeEditCount": 0,
        "totalNumbers": 124,
        "lastUpdated": "2026-02-12T05:20:07.069Z"
      },
      {
        "name": "Hawaii",
        "divisionSlug": "united-states-of-america",
        "slug": "hawaii",
        "invalidCount": 7,
        "autoFixableCount": 0,
        "safeEditCount": 0,
        "totalNumbers": 2285,
        "lastUpdated": "2026-02-12T05:20:13.264Z"
      },
      {
        "name": "Idaho",
        "divisionSlug": "united-states-of-america",
        "slug": "idaho",
        "invalidCount": 3,
        "autoFixableCount": 0,
        "safeEditCount": 0,
        "totalNumbers": 3649,
        "lastUpdated": "2026-02-12T05:20:37.690Z"
      },
      {
        "name": "Illinois",
        "divisionSlug": "united-states-of-america",
        "slug": "illinois",
        "invalidCount": 38,
        "autoFixableCount": 0,
        "safeEditCount": 1,
        "totalNumbers": 29325,
        "lastUpdated": "2026-02-12T05:21:35.532Z"
      },
      {
        "name": "Indiana",
        "divisionSlug": "united-states-of-america",
        "slug": "indiana",
        "invalidCount": 14,
        "autoFixableCount": 0,
        "safeEditCount": 0,
        "totalNumbers": 10679,
        "lastUpdated": "2026-02-12T05:22:09.485Z"
      },
      {
        "name": "Iowa",
        "divisionSlug": "united-states-of-america",
        "slug": "iowa",
        "invalidCount": 0,
        "autoFixableCount": 0,
        "safeEditCount": 2,
        "totalNumbers": 8800,
        "lastUpdated": "2026-02-12T05:22:29.239Z"
      },
      {
        "name": "Kansas",
        "divisionSlug": "united-states-of-america",
        "slug": "kansas",
        "invalidCount": 7,
        "autoFixableCount": 0,
        "safeEditCount": 1,
        "totalNumbers": 7679,
        "lastUpdated": "2026-02-12T05:22:44.298Z"
      },
      {
        "name": "Kentucky",
        "divisionSlug": "united-states-of-america",
        "slug": "kentucky",
        "invalidCount": 12,
        "autoFixableCount": 0,
        "safeEditCount": 0,
        "totalNumbers": 7212,
        "lastUpdated": "2026-02-12T05:23:11.317Z"
      },
      {
        "name": "Louisiana",
        "divisionSlug": "united-states-of-america",
        "slug": "louisiana",
        "invalidCount": 14,
        "autoFixableCount": 0,
        "safeEditCount": 0,
        "totalNumbers": 8093,
        "lastUpdated": "2026-02-12T05:23:30.987Z"
      },
      {
        "name": "Maine",
        "divisionSlug": "united-states-of-america",
        "slug": "maine",
        "invalidCount": 10,
        "autoFixableCount": 1,
        "safeEditCount": 0,
        "totalNumbers": 4259,
        "lastUpdated": "2026-02-12T05:23:42.641Z"
      },
      {
        "name": "Maryland",
        "divisionSlug": "united-states-of-america",
        "slug": "maryland",
        "invalidCount": 24,
        "autoFixableCount": 0,
        "safeEditCount": 0,
        "totalNumbers": 18261,
        "lastUpdated": "2026-02-12T05:24:21.183Z"
      },
      {
        "name": "Massachusetts",
        "divisionSlug": "united-states-of-america",
        "slug": "massachusetts",
        "invalidCount": 34,
        "autoFixableCount": 0,
        "safeEditCount": 0,
        "totalNumbers": 16313,
        "lastUpdated": "2026-02-12T05:24:56.558Z"
      },
      {
        "name": "Michigan",
        "divisionSlug": "united-states-of-america",
        "slug": "michigan",
        "invalidCount": 24,
        "autoFixableCount": 0,
        "safeEditCount": 3,
        "totalNumbers": 26039,
        "lastUpdated": "2026-02-12T05:25:46.470Z"
      },
      {
        "name": "Minnesota",
        "divisionSlug": "united-states-of-america",
        "slug": "minnesota",
        "invalidCount": 19,
        "autoFixableCount": 1,
        "safeEditCount": 2,
        "totalNumbers": 13561,
        "lastUpdated": "2026-02-12T05:26:24.502Z"
      },
      {
        "name": "Mississippi",
        "divisionSlug": "united-states-of-america",
        "slug": "mississippi",
        "invalidCount": 3,
        "autoFixableCount": 0,
        "safeEditCount": 0,
        "totalNumbers": 3996,
        "lastUpdated": "2026-02-12T05:26:38.979Z"
      },
      {
        "name": "Missouri",
        "divisionSlug": "united-states-of-america",
        "slug": "missouri",
        "invalidCount": 25,
        "autoFixableCount": 0,
        "safeEditCount": 1,
        "totalNumbers": 10851,
        "lastUpdated": "2026-02-12T05:27:08.070Z"
      },
      {
        "name": "Montana",
        "divisionSlug": "united-states-of-america",
        "slug": "montana",
        "invalidCount": 0,
        "autoFixableCount": 0,
        "safeEditCount": 0,
        "totalNumbers": 3127,
        "lastUpdated": "2026-02-12T05:27:21.437Z"
      },
      {
        "name": "Nebraska",
        "divisionSlug": "united-states-of-america",
        "slug": "nebraska",
        "invalidCount": 0,
        "autoFixableCount": 0,
        "safeEditCount": 0,
        "totalNumbers": 5570,
        "lastUpdated": "2026-02-12T05:27:38.933Z"
      },
      {
        "name": "Nevada",
        "divisionSlug": "united-states-of-america",
        "slug": "nevada",
        "invalidCount": 0,
        "autoFixableCount": 0,
        "safeEditCount": 0,
        "totalNumbers": 6211,
        "lastUpdated": "2026-02-12T05:27:59.253Z"
      },
      {
        "name": "New Hampshire",
        "divisionSlug": "united-states-of-america",
        "slug": "new-hampshire",
        "invalidCount": 0,
        "autoFixableCount": 0,
        "safeEditCount": 0,
        "totalNumbers": 5770,
        "lastUpdated": "2026-02-12T05:28:10.881Z"
      },
      {
        "name": "New Jersey",
        "divisionSlug": "united-states-of-america",
        "slug": "new-jersey",
        "invalidCount": 9,
        "autoFixableCount": 0,
        "safeEditCount": 1,
        "totalNumbers": 13369,
        "lastUpdated": "2026-02-12T05:28:38.036Z"
      },
      {
        "name": "New Mexico",
        "divisionSlug": "united-states-of-america",
        "slug": "new-mexico",
        "invalidCount": 11,
        "autoFixableCount": 0,
        "safeEditCount": 0,
        "totalNumbers": 6271,
        "lastUpdated": "2026-02-12T05:28:58.141Z"
      },
      {
        "name": "New York",
        "divisionSlug": "united-states-of-america",
        "slug": "new-york",
        "invalidCount": 132,
        "autoFixableCount": 0,
        "safeEditCount": 4,
        "totalNumbers": 54781,
        "lastUpdated": "2026-02-12T05:30:10.363Z"
      },
      {
        "name": "North Carolina",
        "divisionSlug": "united-states-of-america",
        "slug": "north-carolina",
        "invalidCount": 26,
        "autoFixableCount": 0,
        "safeEditCount": 6,
        "totalNumbers": 31222,
        "lastUpdated": "2026-02-12T05:31:12.413Z"
      },
      {
        "name": "North Dakota",
        "divisionSlug": "united-states-of-america",
        "slug": "north-dakota",
        "invalidCount": 0,
        "autoFixableCount": 0,
        "safeEditCount": 0,
        "totalNumbers": 1393,
        "lastUpdated": "2026-02-12T05:31:29.586Z"
      },
      {
        "name": "Northern Mariana Islands",
        "divisionSlug": "united-states-of-america",
        "slug": "northern-mariana-islands",
        "invalidCount": 0,
        "autoFixableCount": 0,
        "safeEditCount": 0,
        "totalNumbers": 52,
        "lastUpdated": "2026-02-12T05:31:31.504Z"
      },
      {
        "name": "Ohio",
        "divisionSlug": "united-states-of-america",
        "slug": "ohio",
        "invalidCount": 28,
        "autoFixableCount": 0,
        "safeEditCount": 2,
        "totalNumbers": 23123,
        "lastUpdated": "2026-02-12T05:32:15.708Z"
      },
      {
        "name": "Oklahoma",
        "divisionSlug": "united-states-of-america",
        "slug": "oklahoma",
        "invalidCount": 16,
        "autoFixableCount": 0,
        "safeEditCount": 0,
        "totalNumbers": 7029,
        "lastUpdated": "2026-02-12T05:32:37.726Z"
      },
      {
        "name": "Oregon",
        "divisionSlug": "united-states-of-america",
        "slug": "oregon",
        "invalidCount": 30,
        "autoFixableCount": 0,
        "safeEditCount": 0,
        "totalNumbers": 21981,
        "lastUpdated": "2026-02-12T05:33:13.173Z"
      },
      {
        "name": "Pennsylvania",
        "divisionSlug": "united-states-of-america",
        "slug": "pennsylvania",
        "invalidCount": 42,
        "autoFixableCount": 0,
        "safeEditCount": 0,
        "totalNumbers": 36545,
        "lastUpdated": "2026-02-12T05:34:08.596Z"
      },
      {
        "name": "Puerto Rico",
        "divisionSlug": "united-states-of-america",
        "slug": "puerto-rico",
        "invalidCount": 24,
        "autoFixableCount": 0,
        "safeEditCount": 0,
        "totalNumbers": 5211,
        "lastUpdated": "2026-02-12T05:34:21.248Z"
      },
      {
        "name": "Rhode Island",
        "divisionSlug": "united-states-of-america",
        "slug": "rhode-island",
        "invalidCount": 22,
        "autoFixableCount": 0,
        "safeEditCount": 0,
        "totalNumbers": 2043,
        "lastUpdated": "2026-02-12T05:34:28.500Z"
      },
      {
        "name": "South Carolina",
        "divisionSlug": "united-states-of-america",
        "slug": "south-carolina",
        "invalidCount": 19,
        "autoFixableCount": 0,
        "safeEditCount": 0,
        "totalNumbers": 10786,
        "lastUpdated": "2026-02-12T05:34:52.973Z"
      },
      {
        "name": "South Dakota",
        "divisionSlug": "united-states-of-america",
        "slug": "south-dakota",
        "invalidCount": 0,
        "autoFixableCount": 0,
        "safeEditCount": 0,
        "totalNumbers": 2013,
        "lastUpdated": "2026-02-12T05:35:11.933Z"
      },
      {
        "name": "Tennessee",
        "divisionSlug": "united-states-of-america",
        "slug": "tennessee",
        "invalidCount": 17,
        "autoFixableCount": 0,
        "safeEditCount": 2,
        "totalNumbers": 11589,
        "lastUpdated": "2026-02-12T05:35:40.836Z"
      },
      {
        "name": "Texas",
        "divisionSlug": "united-states-of-america",
        "slug": "texas",
        "invalidCount": 15,
        "autoFixableCount": 0,
        "safeEditCount": 4,
        "totalNumbers": 54083,
        "lastUpdated": "2026-02-12T05:37:07.891Z"
      },
      {
        "name": "United States Virgin Islands",
        "divisionSlug": "united-states-of-america",
        "slug": "united-states-virgin-islands",
        "invalidCount": 2,
        "autoFixableCount": 0,
        "safeEditCount": 0,
        "totalNumbers": 90,
        "lastUpdated": "2026-02-12T05:37:10.030Z"
      },
      {
        "name": "Utah",
        "divisionSlug": "united-states-of-america",
        "slug": "utah",
        "invalidCount": 22,
        "autoFixableCount": 0,
        "safeEditCount": 0,
        "totalNumbers": 9757,
        "lastUpdated": "2026-02-12T05:37:36.023Z"
      },
      {
        "name": "Vermont",
        "divisionSlug": "united-states-of-america",
        "slug": "vermont",
        "invalidCount": 0,
        "autoFixableCount": 0,
        "safeEditCount": 0,
        "totalNumbers": 2658,
        "lastUpdated": "2026-02-12T05:37:44.191Z"
      },
      {
        "name": "Virginia",
        "divisionSlug": "united-states-of-america",
        "slug": "virginia",
        "invalidCount": 20,
        "autoFixableCount": 0,
        "safeEditCount": 2,
        "totalNumbers": 27030,
        "lastUpdated": "2026-02-12T05:38:50.983Z"
      },
      {
        "name": "Washington",
        "divisionSlug": "united-states-of-america",
        "slug": "washington",
        "invalidCount": 0,
        "autoFixableCount": 0,
        "safeEditCount": 2,
        "totalNumbers": 21302,
        "lastUpdated": "2026-02-12T05:39:37.808Z"
      },
      {
        "name": "West Virginia",
        "divisionSlug": "united-states-of-america",
        "slug": "west-virginia",
        "invalidCount": 1,
        "autoFixableCount": 0,
        "safeEditCount": 0,
        "totalNumbers": 2924,
        "lastUpdated": "2026-02-12T05:39:58.346Z"
      },
      {
        "name": "Wisconsin",
        "divisionSlug": "united-states-of-america",
        "slug": "wisconsin",
        "invalidCount": 16,
        "autoFixableCount": 0,
        "safeEditCount": 1,
        "totalNumbers": 15970,
        "lastUpdated": "2026-02-12T05:40:42.230Z"
      },
      {
        "name": "Wyoming",
        "divisionSlug": "united-states-of-america",
        "slug": "wyoming",
        "invalidCount": 0,
        "autoFixableCount": 0,
        "safeEditCount": 0,
        "totalNumbers": 2418,
        "lastUpdated": "2026-02-12T05:41:03.824Z"
      }
    ]
  },
  "botEnabled": true
}